proxypay.py
proxypay_py-1.0.0.dist-info/METADATA
proxypay_py-1.0.0.dist-info/RECORD
proxypay_py-1.0.0.dist-info/WHEEL
proxypay_py-1.0.0.dist-info/top_level.txt
